web_search_agent/__init__.py
web_search_agent/agent.py
web_search_agent/config.py
web_search_agent/models.py
web_search_agent/prompts/__init__.py
web_search_agent/prompts/initial.py
web_search_agent/prompts/section.py
web_search_agent/utils/__init__.py
web_search_agent/utils/search.py
web_search_agent-0.2.0.dist-info/METADATA
web_search_agent-0.2.0.dist-info/WHEEL
web_search_agent-0.2.0.dist-info/entry_points.txt
web_search_agent-0.2.0.dist-info/top_level.txt
web_search_agent-0.2.0.dist-info/RECORD
