Metadata-Version: 2.4
Name: web-search-agent
Version: 0.2.0
Summary: An intelligent web search agent that provides structured results
Home-page: https://github.com/leepokai/web-search-agent
Author: leepokai
Author-email: leepokai <kevin2005ha@gmail.com>
License: MIT License
Project-URL: Homepage, https://github.com/leepokai/web-search-agent
Project-URL: Bug Tracker, https://github.com/leepokai/web-search-agent/issues
Classifier: Programming Language :: Python :: 3
Classifier: Programming Language :: Python :: 3.11
Classifier: License :: OSI Approved :: MIT License
Classifier: Operating System :: OS Independent
Requires-Python: >=3.11
Requires-Dist: open-deep-research
Requires-Dist: python-dotenv
Requires-Dist: langchain-openai
Requires-Dist: langchain-core
Requires-Dist: pydantic
Requires-Dist: tavily-python
Dynamic: author
Dynamic: home-page
Dynamic: requires-python
